PyZIPIN/ZIPDecode.py
PyZIPIN/ZIPInfo.db
PyZIPIN/__init__.py
PyZIPIN/createDB.py
PyZIPIN/populateDB.py
PyZIPIN-0.1.2.dist-info/DESCRIPTION.rst
PyZIPIN-0.1.2.dist-info/METADATA
PyZIPIN-0.1.2.dist-info/RECORD
PyZIPIN-0.1.2.dist-info/WHEEL
PyZIPIN-0.1.2.dist-info/metadata.json
PyZIPIN-0.1.2.dist-info/top_level.txt
