Metadata-Version: 2.0
Name: PyZIPIN
Version: 0.1.2
Summary: A python3 library providing information of ZIP codes of India based on data from data.gov.in(2018)
Home-page: https://github.com/ash2shukla/PyZIPIN
Author: Ashish Shukla
Author-email: ash2shukla@gmail.com
License: MIT
Download-URL: https://github.com/ash2shukla/RailIN/archive/0.1.2.tar.gz
Keywords: zipcodes,pincode,india,data.gov.in
Platform: UNKNOWN
Requires-Dist: sqlalchemy
